pyweclapp/__init__.py
pyweclapp/custom_attributes/__init__.py
pyweclapp/custom_attributes/config.py
pyweclapp/custom_attributes/custom_attribute_class.py
pyweclapp/time_functions/__init__.py
pyweclapp/weclapp/__init__.py
pyweclapp/weclapp/config.py
pyweclapp/weclapp_classes/__init__.py
pyweclapp/weclapp_classes/article_model.py
pyweclapp/weclapp_classes/currency_model.py
pyweclapp/weclapp_classes/extra_info_for_app_model.py
pyweclapp/weclapp_classes/incoming_goods_model.py
pyweclapp/weclapp_classes/party_model.py
pyweclapp/weclapp_classes/purchase_order_model.py
pyweclapp/weclapp_classes/quotation_model.py
pyweclapp/weclapp_classes/sales_invoice_model.py
pyweclapp/weclapp_classes/sales_order_model.py
pyweclapp/weclapp_classes/shipment_model.py
pyweclapp/weclapp_classes/blueprints/__init__.py
pyweclapp/weclapp_classes/blueprints/config.py
pyweclapp/weclapp_classes/blueprints/custom_attributes_model.py
pyweclapp/weclapp_classes/blueprints/weclapp_class_creator.py
pyweclapp/weclapp_document/__init__.py
pyweclapp/weclapp_document/document.py
pyweclapp-0.1.21.dist-info/licenses/LICENSE
pyweclapp-0.1.21.dist-info/METADATA
pyweclapp-0.1.21.dist-info/WHEEL
pyweclapp-0.1.21.dist-info/top_level.txt
pyweclapp-0.1.21.dist-info/RECORD
