Metadata-Version: 2.4
Name: pyweclapp
Version: 0.1.21
Summary: Provides methods, classes and classbuilders to interact with the Weclapp API
Home-page: https://github.com/AltruanGmbH/pyweclapp
Author: Altruan GmbH
Author-email: admin@altruan.de
License: MIT
Classifier: License :: OSI Approved :: MIT License
Classifier: Programming Language :: Python :: 3.10
Classifier: Operating System :: OS Independent
Requires-Python: >=3.9
License-File: LICENSE
Requires-Dist: annotated-types==0.6.0
Requires-Dist: attrs==23.1.0
Requires-Dist: certifi==2023.11.17
Requires-Dist: charset-normalizer==3.3.2
Requires-Dist: idna==3.4
Requires-Dist: jsonschema==4.20.0
Requires-Dist: jsonschema-specifications==2023.11.1
Requires-Dist: pydantic==2.5.2
Requires-Dist: pydantic_core==2.14.5
Requires-Dist: pytz==2023.3.post1
Requires-Dist: referencing==0.31.0
Requires-Dist: requests==2.31.0
Requires-Dist: rpds-py==0.13.1
Requires-Dist: typing_extensions>=4.8.0
Requires-Dist: urllib3==2.1.0
Provides-Extra: dev
Requires-Dist: twine>=4.0.2; extra == "dev"
Dynamic: author
Dynamic: author-email
Dynamic: classifier
Dynamic: description
Dynamic: description-content-type
Dynamic: home-page
Dynamic: license
Dynamic: license-file
Dynamic: provides-extra
Dynamic: requires-dist
Dynamic: requires-python
Dynamic: summary
